odoo/addons/endpoint_cache_preheat/README.rst
odoo/addons/endpoint_cache_preheat/__init__.py
odoo/addons/endpoint_cache_preheat/__manifest__.py
odoo/addons/endpoint_cache_preheat/data/cron.xml
odoo/addons/endpoint_cache_preheat/data/job_channel.xml
odoo/addons/endpoint_cache_preheat/data/job_function.xml
odoo/addons/endpoint_cache_preheat/i18n/endpoint_cache_preheat.pot
odoo/addons/endpoint_cache_preheat/i18n/it.po
odoo/addons/endpoint_cache_preheat/models/__init__.py
odoo/addons/endpoint_cache_preheat/models/endpoint_mixin.py
odoo/addons/endpoint_cache_preheat/readme/CONFIGURE.md
odoo/addons/endpoint_cache_preheat/readme/CONTRIBUTORS.md
odoo/addons/endpoint_cache_preheat/readme/DESCRIPTION.md
odoo/addons/endpoint_cache_preheat/static/description/icon.png
odoo/addons/endpoint_cache_preheat/static/description/index.html
odoo/addons/endpoint_cache_preheat/tests/__init__.py
odoo/addons/endpoint_cache_preheat/tests/test_endpoint.py
odoo/addons/endpoint_cache_preheat/views/endpoint_view.xml
odoo_addon_endpoint_cache_preheat-18.0.1.0.0.2.dist-info/METADATA
odoo_addon_endpoint_cache_preheat-18.0.1.0.0.2.dist-info/WHEEL
odoo_addon_endpoint_cache_preheat-18.0.1.0.0.2.dist-info/top_level.txt
odoo_addon_endpoint_cache_preheat-18.0.1.0.0.2.dist-info/RECORD
